ezcliy/__init__.py
ezcliy/commands.py
ezcliy/exceptions.py
ezcliy/helpman.py
ezcliy/parameters.py
ezcliy/positional.py
ezcliy-0.3.1.dist-info/LICENSE
ezcliy-0.3.1.dist-info/METADATA
ezcliy-0.3.1.dist-info/WHEEL
ezcliy-0.3.1.dist-info/top_level.txt
ezcliy-0.3.1.dist-info/RECORD
