Metadata-Version: 2.1
Name: ezcliy
Version: 0.3.1
Summary: Framework for creating CLI tools
Home-page: https://github.com/kpostekk/ezcliy
Author: Krystian Postek
Author-email: krystian@postek.eu
License: MIT
Project-URL: Repository, https://github.com/kpostekk/ezcliy/
Project-URL: Docs, https://ezcliy.readthedocs.io/en/latest/
Platform: UNKNOWN
Classifier: Programming Language :: Python :: 3.9
Classifier: Environment :: Console
Classifier: Intended Audience :: Developers
Classifier: Operating System :: OS Independent
Classifier: License :: OSI Approved :: Apache Software License
License-File: LICENSE
Requires-Dist: sty
